docs/sphinx/conf.py
liguard/__init__.py
liguard/liguard_cmd.py
liguard/liguard_gui.py
liguard/liguard_profiler.py
liguard/algo/__init__.py
liguard/algo/calib.py
liguard/algo/camera.py
liguard/algo/label.py
liguard/algo/lidar.py
liguard/algo/post.py
liguard/algo/pre.py
liguard/algo/utils.py
liguard/algo/nn/__init__.py
liguard/algo/non_nn/DHistDPP.py
liguard/algo/non_nn/STDF.py
liguard/algo/non_nn/__init__.py
liguard/calib/__init__.py
liguard/calib/file_io.py
liguard/calib/handler_ips300plus.py
liguard/calib/handler_kitti.py
liguard/calib/handler_sustechpoints.py
liguard/calib/utils.py
liguard/examples/simple_pipeline/base_config.yml
liguard/examples/simple_pipeline/dataset/calibs/000000.txt
liguard/examples/simple_pipeline/dataset/calibs/000001.txt
liguard/examples/simple_pipeline/dataset/calibs/000002.txt
liguard/examples/simple_pipeline/dataset/calibs/000003.txt
liguard/examples/simple_pipeline/dataset/calibs/000004.txt
liguard/examples/simple_pipeline/dataset/images/000000.png
liguard/examples/simple_pipeline/dataset/images/000001.png
liguard/examples/simple_pipeline/dataset/images/000002.png
liguard/examples/simple_pipeline/dataset/images/000003.png
liguard/examples/simple_pipeline/dataset/images/000004.png
liguard/examples/simple_pipeline/dataset/labels/000000.txt
liguard/examples/simple_pipeline/dataset/labels/000001.txt
liguard/examples/simple_pipeline/dataset/labels/000002.txt
liguard/examples/simple_pipeline/dataset/labels/000003.txt
liguard/examples/simple_pipeline/dataset/labels/000004.txt
liguard/examples/simple_pipeline/dataset/pointclouds/000000.bin
liguard/examples/simple_pipeline/dataset/pointclouds/000001.bin
liguard/examples/simple_pipeline/dataset/pointclouds/000002.bin
liguard/examples/simple_pipeline/dataset/pointclouds/000003.bin
liguard/examples/simple_pipeline/dataset/pointclouds/000004.bin
liguard/gui/__init__.py
liguard/gui/config_gui.py
liguard/gui/gui_utils.py
liguard/gui/logger_gui.py
liguard/img/__init__.py
liguard/img/file_io.py
liguard-2.1.5.post3.dist-info/licenses/LICENSE.txt
liguard-2.1.5.post3.dist-info/METADATA
liguard-2.1.5.post3.dist-info/WHEEL
liguard-2.1.5.post3.dist-info/entry_points.txt
liguard-2.1.5.post3.dist-info/top_level.txt
liguard-2.1.5.post3.dist-info/RECORD
