Metadata-Version: 2.4
Name: LiGuard
Version: 2.1.5.post3
Summary: A research-purposed, GUI-powered, Python-based framework that allows easy development of dynamic point-cloud (and accompanying image) data processing pipelines.
Author-email: Muhammad Shahbaz <m.shahbaz.kharal@outlook.com>
License-Expression: MIT
Project-URL: Homepage, https://github.com/m-shahbaz-kharal/LiGuard-2.x
Keywords: point-cloud,image,processing,pipeline,dynamic,GUI,research,development,framework
Classifier: Programming Language :: Python :: 3.10
Classifier: Programming Language :: Python :: 3.11
Classifier: Programming Language :: Python :: 3.12
Classifier: Development Status :: 3 - Alpha
Classifier: Environment :: Win32 (MS Windows)
Classifier: Environment :: X11 Applications
Classifier: Environment :: MacOS X
Classifier: Intended Audience :: Developers
Classifier: Intended Audience :: Education
Classifier: Intended Audience :: Other Audience
Classifier: Intended Audience :: Science/Research
Classifier: Natural Language :: English
Classifier: Operating System :: Microsoft :: Windows
Classifier: Operating System :: POSIX :: Linux
Classifier: Operating System :: MacOS :: MacOS X
Classifier: Topic :: Scientific/Engineering :: Image Processing
Classifier: Topic :: Scientific/Engineering :: Visualization
Classifier: Topic :: Multimedia :: Graphics :: Viewers
Classifier: Topic :: Utilities
Requires-Python: >=3.10
License-File: LICENSE.txt
Requires-Dist: matplotlib
Requires-Dist: numpy<2.0.0
Requires-Dist: open3d==0.19.0
Requires-Dist: opencv-python
Requires-Dist: pynput
Requires-Dist: pillow
Requires-Dist: pyyaml
Requires-Dist: scipy
Requires-Dist: tqdm
Requires-Dist: dask
Dynamic: license-file
